aoe2netwrapper/__init__.py
aoe2netwrapper/api.py
aoe2netwrapper/converters.py
aoe2netwrapper/exceptions.py
aoe2netwrapper/nightbot.py
aoe2netwrapper/models/__init__.py
aoe2netwrapper/models/last_match.py
aoe2netwrapper/models/leaderboard.py
aoe2netwrapper/models/lobbies.py
aoe2netwrapper/models/match.py
aoe2netwrapper/models/match_history.py
aoe2netwrapper/models/matches.py
aoe2netwrapper/models/num_online.py
aoe2netwrapper/models/rating_history.py
aoe2netwrapper/models/strings.py
aoe2netwrapper-0.4.0.dist-info/METADATA
aoe2netwrapper-0.4.0.dist-info/WHEEL
aoe2netwrapper-0.4.0.dist-info/licenses/LICENSE
aoe2netwrapper-0.4.0.dist-info/RECORD
