Metadata-Version: 2.3
Name: aoe2netwrapper
Version: 0.4.0
Summary: My Python wrapper for the aoe2.net data API
Project-URL: homepage, https://github.com/fsoubelet/AoE2NetAPIWrapper
Project-URL: repository, https://github.com/fsoubelet/AoE2NetAPIWrapper
Project-URL: documentation, https://fsoubelet.github.io/AoE2NetAPIWrapper/
Author-email: Felix Soubelet <felix.soubelet@cern.ch>
License-Expression: MIT
License-File: LICENSE
Keywords: API,AoE2,Utility
Classifier: Development Status :: 4 - Beta
Classifier: Intended Audience :: Developers
Classifier: Intended Audience :: End Users/Desktop
Classifier: License :: OSI Approved :: MIT License
Classifier: Natural Language :: English
Classifier: Programming Language :: Python
Classifier: Programming Language :: Python :: 3 :: Only
Classifier: Programming Language :: Python :: 3.9
Classifier: Programming Language :: Python :: 3.10
Classifier: Programming Language :: Python :: 3.11
Classifier: Programming Language :: Python :: 3.12
Classifier: Programming Language :: Python :: Implementation :: CPython
Classifier: Topic :: Games/Entertainment
Classifier: Topic :: Utilities
Classifier: Typing :: Typed
Requires-Python: >=3.10
Requires-Dist: loguru<1.0
Requires-Dist: pydantic>=2.5
Requires-Dist: requests>=2.30
Provides-Extra: all
Requires-Dist: numpy<2.0; extra == 'all'
Requires-Dist: pandas>=2.0; extra == 'all'
Requires-Dist: portray>=1.4; extra == 'all'
Requires-Dist: pytest-cov>=2.9; extra == 'all'
Requires-Dist: pytest>=7.0; extra == 'all'
Requires-Dist: responses>=0.20; extra == 'all'
Provides-Extra: dataframe
Requires-Dist: pandas>=2.0; extra == 'dataframe'
Provides-Extra: docs
Requires-Dist: numpy<2.0; extra == 'docs'
Requires-Dist: pandas>=2.0; extra == 'docs'
Requires-Dist: portray>=1.4; extra == 'docs'
Provides-Extra: test
Requires-Dist: pandas>=2.0; extra == 'test'
Requires-Dist: pytest-cov>=2.9; extra == 'test'
Requires-Dist: pytest>=7.0; extra == 'test'
Requires-Dist: responses>=0.20; extra == 'test'
